baseweb_plugin_template/__init__.py
baseweb_plugin_template/module.py
baseweb_plugin_template/components/__init__.py
baseweb_plugin_template/components/page.js
baseweb_plugin_template/static/__init__.py
baseweb_plugin_template/static/images/__init__.py
baseweb_plugin_template/static/images/baseball.png
baseweb_plugin_template-0.1.0.dist-info/LICENSE.txt
baseweb_plugin_template-0.1.0.dist-info/LICENSE.txt.backup
baseweb_plugin_template-0.1.0.dist-info/METADATA
baseweb_plugin_template-0.1.0.dist-info/WHEEL
baseweb_plugin_template-0.1.0.dist-info/top_level.txt
baseweb_plugin_template-0.1.0.dist-info/RECORD
