Metadata-Version: 2.1
Name: baseweb-plugin-template
Version: 0.1.0
Summary: an example baseweb plugin
Home-page: https://github.com/christophevg/baseweb-plugin-template
Author: Christophe VG
License: MIT
Keywords: example baseweb plugin
Platform: UNKNOWN
Classifier: Programming Language :: Python
Classifier: Intended Audience :: Developers
Classifier: Development Status :: 4 - Beta
Classifier: License :: OSI Approved :: MIT License
Classifier: Environment :: Plugins
Classifier: Environment :: Web Environment
Classifier: Programming Language :: Python :: 3
Requires-Dist: baseweb
